codes/sandbox_verilog/shift_register.v
module free_run_shift_reg
  #(parameter N=8)
  (
    input wire clk, reset,
    input wire s_in,
    output wire s_out
  );

  reg [N-1:0] r_reg;
  wire [N-1:0] r_next;

  always @(posedge clk, negedge reset)
  begin
    if (~reset)
      r_reg <= 0;
    else
      r_reg <= r_next;
  end

  assign r_next = {s_in, r_reg[N-1:1]};
  assign s_out = r_reg[0];

endmodule


`timescale 1ns / 1ps

module stimulus;
  reg clk;
  reg reset;

  reg s_in;
  wire s_out;

  free_run_shift_reg #(2) s1 (
    .clk(clk),
    .reset(reset),
    .s_in(s_in),
    .s_out(s_out)
    );

  integer i, j;

  initial begin
    clk = 0;
    for(i = 0; i<=40; i=i+1) begin
      #10 clk = ~clk;  // period 20 ns (50 MHz)
    end
  end

  initial begin
    $dumpfile("shift_register.vcd");
    $dumpvars(0, stimulus);

    s_in = 0;
    reset = 1;

    #2 s_in = 0; reset = 0;
    #2 reset = 1;

    for(j = 0; j<=10; j=j+1) begin
      #20 s_in = ~s_in;
    end

    #20 s_in = 1;
    #20 s_in = 1;
    #20 s_in = 0;
    #20 s_in = 1;
    #20 s_in = 1;
    #20 s_in = 0;
    #20 s_in = 1;
    #20 s_in = 1;
    #20 s_in = 0;

  end

  initial begin
    $monitor("clk s_in s_out");
  end

  initial begin
    $monitor("%8d %d %b %b", $time, clk, s_in, s_out);
  end

endmodule

codes/sandbox_verilog/shift_register.vcd
$date
	Sun Jan 29 04:29:04 2017
$end
$version
	Icarus Verilog
$end
$timescale
	1ps
$end
$scope module stimulus $end
$var wire 1 ! s_out $end
$var reg 1 " clk $end
$var integer 32 # i [31:0] $end
$var integer 32 $ j [31:0] $end
$var reg 1 % reset $end
$var reg 1 & s_in $end
$scope module s1 $end
$var wire 1 ' clk $end
$var wire 2 ( r_next [1:0] $end
$var wire 1 ) reset $end
$var wire 1 * s_in $end
$var wire 1 ! s_out $end
$var reg 2 + r_reg [1:0] $end
$upscope $end
$upscope $end
$enddefinitions $end
#0
$dumpvars
bx +
0*
1)
b0x (
0'
0&
1%
bx $
b0 #
0"
x!
$end
#2000
b0 (
0!
b0 +
0%
0)
#4000
b0 $
1%
1)
#10000
b1 #
1"
1'
#20000
b10 #
0"
0'
#24000
b1 $
1&
1*
b10 (
#30000
b11 (
b10 +
b11 #
1"
1'
#40000
b100 #
0"
0'
#44000
b10 $
0&
0*
b1 (
#50000
b0 (
1!
b1 +
b101 #
1"
1'
#60000
b110 #
0"
0'
#64000
b11 $
1&
1*
b10 (
#70000
b11 (
0!
b10 +
b111 #
1"
1'
#80000
b1000 #
0"
0'
#84000
b100 $
0&
0*
b1 (
#90000
b0 (
1!
b1 +
b1001 #
1"
1'
#100000
b1010 #
0"
0'
#104000
b101 $
1&
1*
b10 (
#110000
b11 (
0!
b10 +
b1011 #
1"
1'
#120000
b1100 #
0"
0'
#124000
b110 $
0&
0*
b1 (
#130000
b0 (
1!
b1 +
b1101 #
1"
1'
#140000
b1110 #
0"
0'
#144000
b111 $
1&
1*
b10 (
#150000
b11 (
0!
b10 +
b1111 #
1"
1'
#160000
b10000 #
0"
0'
#164000
b1000 $
0&
0*
b1 (
#170000
b0 (
1!
b1 +
b10001 #
1"
1'
#180000
b10010 #
0"
0'
#184000
b1001 $
1&
1*
b10 (
#190000
b11 (
0!
b10 +
b10011 #
1"
1'
#200000
b10100 #
0"
0'
#204000
b1010 $
0&
0*
b1 (
#210000
b0 (
1!
b1 +
b10101 #
1"
1'
#220000
b10110 #
0"
0'
#224000
b1011 $
1&
1*
b10 (
#230000
b11 (
0!
b10 +
b10111 #
1"
1'
#240000
b11000 #
0"
0'
#250000
1!
b11 +
b11001 #
1"
1'
#260000
b11010 #
0"
0'
#270000
b11011 #
1"
1'
#280000
b11100 #
0"
0'
#284000
0&
0*
b1 (
#290000
b0 (
b1 +
b11101 #
1"
1'
#300000
b11110 #
0"
0'
#304000
1&
1*
b10 (
#310000
b11 (
0!
b10 +
b11111 #
1"
1'
#320000
b100000 #
0"
0'
#330000
1!
b11 +
b100001 #
1"
1'
#340000
b100010 #
0"
0'
#344000
0&
0*
b1 (
#350000
b0 (
b1 +
b100011 #
1"
1'
#360000
b100100 #
0"
0'
#364000
1&
1*
b10 (
#370000
b11 (
0!
b10 +
b100101 #
1"
1'
#380000
b100110 #
0"
0'
#390000
1!
b11 +
b100111 #
1"
1'
#400000
b101000 #
0"
0'
#404000
0&
0*
b1 (
#410000
b0 (
b1 +
b101001 #
1"
1'
