Modul5/JK_ff_v3.v
module JK_ff(J, K, clk, Q, Qb);
  output reg Q, Qb;
  input wire J, K, clk;

  initial begin
    Q  = 1'b0;
    Qb = 1'b1;
  end

  always @ (posedge clk)
  begin
    case({J,K})
      2'b00: begin Q =  Q; Qb =  Qb; end // no change
      2'b01: begin Q =  0; Qb =   1; end
	  	2'b10: begin Q =  1; Qb =   0; end
	  	2'b11: begin Q = ~Q; Qb = ~Qb; end  // toggle
	  endcase
   end

endmodule

codes/basic_sequential/test_JK_ff.v
`timescale 1ns / 1ps
`include "JK_ff_v3.v"

module test_JK_ff();

  reg J, K;
  wire Q, Qb;
  reg clk;
  reg rst;

  JK_ff UUT( J, K, clk, Q, Qb );

  initial clk = 0;
  always begin
    #10 clk = ~clk;
  end

  initial begin
    $dumpfile("test_JK_ff.vcd");
    $dumpvars(0, test_JK_ff);
  end

  initial begin
    $monitor("t=%8d clk=%b rst=%b J=%b K=%b Q=%b Qb=%b", $time, clk, rst, J, K, Q, Qb);
  end

  initial begin
    J = 1;
    K = 1;
    rst = 1;
    #1 J = 1; K = 0; // set
    #20 J = 1; K = 1; // toggle
    #20 J = 1; K = 1; // toggle
    #20 J = 1; K = 1; // toggle
    //#40 K = 0;
    #50 $finish;
  end

endmodule

codes/basic_sequential/test_JK_ff.vcd
$date
	Mon Feb 27 00:38:08 2017
$end
$version
	Icarus Verilog
$end
$timescale
	1ps
$end
$scope module test_JK_ff $end
$var wire 1 ! Q $end
$var wire 1 " Qb $end
$var reg 1 # J $end
$var reg 1 $ K $end
$var reg 1 % clk $end
$var reg 1 & rst $end
$scope module UUT $end
$var wire 1 ' J $end
$var wire 1 ( K $end
$var wire 1 ) clk $end
$var reg 1 * Q $end
$var reg 1 + Qb $end
$upscope $end
$upscope $end
$enddefinitions $end
#0
$dumpvars
1+
0*
0)
1(
1'
1&
0%
1$
1#
1"
0!
$end
#1000
0$
0(
#10000
0+
0"
1*
1!
1%
1)
#20000
0%
0)
#21000
1$
1(
#30000
1+
1"
0*
0!
1%
1)
#40000
0%
0)
#50000
0+
0"
1*
1!
1%
1)
#60000
0%
0)
#70000
1+
1"
0*
0!
1%
1)
#80000
0%
0)
#90000
0+
0"
1*
1!
1%
1)
#100000
0%
0)
#110000
1+
1"
0*
0!
1%
1)
