codes/basic_sequential/counter_4bit_up.v
module counter_4bit_up( clock, reset, enable, count );

  input clock;
  input reset;
  input enable;
  output reg [3:0] count;

  always @(posedge clock, enable, reset)
  begin
    if(reset == 1'b1)
      count <= 4'b0000;
    else if(enable == 1'b1)
      count <= count + 1'b1;
  end

endmodule

codes/tests/test_counter_4bit_up.v
`timescale 1ns / 1ps
`include "counter_4bit_up.v"

module test_counter_4bit_up;

  reg clock, reset, enable;
  wire [3:0] count;

  counter_4bit_up UUT( clock, reset, enable, count );

  initial clock = 0;
  always begin
    #10 clock = ~clock;
  end

  initial begin
    reset = 0;
    enable = 0;
  end

  initial begin
    //
    $dumpfile("test_counter_4bit_up.vcd");
    $dumpvars(0, test_counter_4bit_up);
    //
    $display("time clock reset enable count");
    $monitor("%5d %b %b %b %b", $time, clock, reset, enable, count);

    #10 reset = 1;
    #10 reset = 0; enable = 1;
    #200 $finish;
  end

endmodule

codes/test_counter_4bit_up.vcd
$date
	Mon Feb 13 11:32:42 2017
$end
$version
	Icarus Verilog
$end
$timescale
	1ps
$end
$scope module test_counter_4bit_up $end
$var wire 4 ! count [3:0] $end
$var reg 1 " clock $end
$var reg 1 # enable $end
$var reg 1 $ reset $end
$scope module UUT $end
$var wire 1 % clock $end
$var wire 1 & enable $end
$var wire 1 ' reset $end
$var reg 4 ( count [3:0] $end
$upscope $end
$upscope $end
$enddefinitions $end
#0
$dumpvars
bx (
0'
0&
0%
0$
0#
0"
bx !
$end
#10000
b0 (
b0 !
1$
1'
1"
1%
#20000
1#
1&
0$
0'
0"
0%
#30000
b1 (
b1 !
1"
1%
#40000
0"
0%
#50000
b10 (
b10 !
1"
1%
#60000
0"
0%
#70000
b11 (
b11 !
1"
1%
#80000
0"
0%
#90000
b100 (
b100 !
1"
1%
#100000
0"
0%
#110000
b101 (
b101 !
1"
1%
#120000
0"
0%
#130000
b110 (
b110 !
1"
1%
#140000
0"
0%
#150000
b111 (
b111 !
1"
1%
#160000
0"
0%
#170000
b1000 (
b1000 !
1"
1%
#180000
0"
0%
#190000
b1001 (
b1001 !
1"
1%
#200000
0"
0%
#210000
b1010 (
b1010 !
1"
1%
